{
	"AR_menu_title": "AR United Forces",
	"AR_menu_desc": "More unit and more fun(...?)",
	"AR_Lang_title": "Language",
	"AR_Lang_desc": "Thanks to Schrodinger_Sig :D",
	"AR_Lang_en": "Engligh",
	"AR_Lang_zh_cn": "简体中文",
	"AR_A_title": "SWAT/FBI Units",
	"AR_R_title": "(REQ SSR)Rassian Mercenaries",
	"AR_R_title_R": "Allow Rassian Mercenaries spawn",
	"AR_Z_title": "(REQ SSR)Zombies",
	"AR_Z_title_Z": "Allow Zombies spawn",
	"AR_M_title": "(REQ SSR)Murkywater",
	"AR_M_title_M": "Allow Murkywater spawn",
	"AR_O_title": "(REQ SSR)ZEAL Unit",
	"AR_A_desc": "SWAT, FBI, Gensec, and ZEAL(only appear in DW/DS difficunty)",
	"AR_R_desc": "Rassian Mercenaries that only appear in Boiling Point",
	"AR_Z_desc": "Zombie SWAT/FBI that only appear in Cursed Kill Room",
	"AR_M_desc": "Murkywater that appear in Hell's Island",
	"AR_O_desc": "Allow ZEAL Unit spawn in non-DW/DS difficulty.",
	"ARA_menu_title": "Normal Heists",
	"ARA_menu_desc": "Most of Heists",
	"ARR_menu_title": "Russia Heists",
	"ARR_menu_desc": "Boiling Point only",
	"ARZ_menu_title": "Events Heists",
	"ARZ_menu_desc": "Cursed Kill Room only",
	"ARM_menu_title": "Murkywater Heists",
	"ARM_menu_desc": "Beneath the Mountain, Henry's Rock, Hell's Island and The White House"
}